odoo/addons/shopinvader_locomotive_wishlist/README.rst
odoo/addons/shopinvader_locomotive_wishlist/__init__.py
odoo/addons/shopinvader_locomotive_wishlist/__manifest__.py
odoo/addons/shopinvader_locomotive_wishlist/components/__init__.py
odoo/addons/shopinvader_locomotive_wishlist/components/event_listeners.py
odoo/addons/shopinvader_locomotive_wishlist/components/shopinvader_partner_export_mapper.py
odoo/addons/shopinvader_locomotive_wishlist/i18n/shopinvader_locomotive_wishlist.pot
odoo/addons/shopinvader_locomotive_wishlist/readme/CONTRIBUTORS.rst
odoo/addons/shopinvader_locomotive_wishlist/readme/DESCRIPTION.rst
odoo/addons/shopinvader_locomotive_wishlist/services/__init__.py
odoo/addons/shopinvader_locomotive_wishlist/services/wishlist.py
odoo/addons/shopinvader_locomotive_wishlist/static/description/index.html
odoo/addons/shopinvader_locomotive_wishlist/tests/__init__.py
odoo/addons/shopinvader_locomotive_wishlist/tests/test_shopinvader_partner.py
odoo/addons/shopinvader_locomotive_wishlist/tests/test_wishlist.py
odoo13_addon_shopinvader_locomotive_wishlist-13.0.1.2.0.dist-info/METADATA
odoo13_addon_shopinvader_locomotive_wishlist-13.0.1.2.0.dist-info/WHEEL
odoo13_addon_shopinvader_locomotive_wishlist-13.0.1.2.0.dist-info/top_level.txt
odoo13_addon_shopinvader_locomotive_wishlist-13.0.1.2.0.dist-info/RECORD
