Metadata-Version: 2.1
Name: odoo13-addon-shopinvader-locomotive-wishlist
Version: 13.0.1.2.0
Summary: Synchronize wishlist details to Locomotive users record.
Home-page: https://github.com/shopinvader/odoo-shopinvader
Author: Camptocamp
License: AGPL-3
Platform: UNKNOWN
Classifier: Programming Language :: Python
Classifier: Framework :: Odoo
Classifier: License :: OSI Approved :: GNU Affero General Public License v3
Requires-Python: >=3.5
Requires-Dist: odoo13-addon-shopinvader-locomotive
Requires-Dist: odoo13-addon-shopinvader-wishlist
Requires-Dist: odoo (<13.1dev,>=13.0a)
